emptygpt/__init__.py
emptygpt/__main__.py
emptygpt/api.py
emptygpt/cli.py
emptygpt/generator.py
emptygpt-0.1.3.dist-info/licenses/LICENSE
emptygpt-0.1.3.dist-info/METADATA
emptygpt-0.1.3.dist-info/WHEEL
emptygpt-0.1.3.dist-info/entry_points.txt
emptygpt-0.1.3.dist-info/top_level.txt
emptygpt-0.1.3.dist-info/RECORD
