Metadata-Version: 2.4
Name: emptygpt
Version: 0.1.3
Summary: Generate EmptyGPT-style jargon paragraphs.
Author: Decentricity
License: MIT
Keywords: generator,text,parody,snowclone,jargon
Classifier: Programming Language :: Python :: 3
Classifier: License :: OSI Approved :: MIT License
Classifier: Operating System :: OS Independent
Requires-Python: >=3.9
License-File: LICENSE
Dynamic: license-file
